LICENSE
MANIFEST.in
README.rst
async_ttl.py
setup.cfg
setup.py
async_ttl.egg-info/PKG-INFO
async_ttl.egg-info/SOURCES.txt
async_ttl.egg-info/dependency_links.txt
async_ttl.egg-info/not-zip-safe
async_ttl.egg-info/top_level.txt