Metadata-Version: 2.1
Name: async-ttl
Version: 0.0.4
Summary: Asyncio in memory cache with ttl
Home-page: https://github.com/krkd/async_ttl
Author: Dima Kruk
Author-email: krkdima@gmail.com
License: UNKNOWN
Keywords: asyncio,ttl,ttl_cache
Platform: UNKNOWN
Classifier: Development Status :: 2 - Pre-Alpha
Classifier: Intended Audience :: Developers
Classifier: License :: OSI Approved :: Apache Software License
Classifier: Programming Language :: Python
Classifier: Programming Language :: Python :: 3
Classifier: Programming Language :: Python :: 3.6
Classifier: Programming Language :: Python :: 3.7
Requires-Python: >=3.6.0
